wf_airtable_api_schema/__init__.py
wf_airtable_api_schema/models/__init__.py
wf_airtable_api_schema/models/auto_response_email_template.py
wf_airtable_api_schema/models/base_model.py
wf_airtable_api_schema/models/contact_info.py
wf_airtable_api_schema/models/educators.py
wf_airtable_api_schema/models/educators_schools.py
wf_airtable_api_schema/models/geo_area_contacts.py
wf_airtable_api_schema/models/geo_area_target_communities.py
wf_airtable_api_schema/models/geo_areas.py
wf_airtable_api_schema/models/guides_schools.py
wf_airtable_api_schema/models/hubs.py
wf_airtable_api_schema/models/languages.py
wf_airtable_api_schema/models/montessori_certifications.py
wf_airtable_api_schema/models/partners.py
wf_airtable_api_schema/models/pods.py
wf_airtable_api_schema/models/response.py
wf_airtable_api_schema/models/schools.py
wf_airtable_api_schema/models/ssj_fillout_get_involved.py
wf_airtable_api_schema/models/ssj_typeform_start_a_school.py
wf_airtable_api_schema/models/target_communities.py
wf_airtable_api_schema/models/utils.py
wf_airtable_api_schema-0.6.7.dist-info/LICENSE
wf_airtable_api_schema-0.6.7.dist-info/METADATA
wf_airtable_api_schema-0.6.7.dist-info/WHEEL
wf_airtable_api_schema-0.6.7.dist-info/RECORD
