Metadata-Version: 2.1
Name: wf-airtable-api-schema
Version: 0.6.7
Summary: Simple package defining a schema translation layer between the client and Airtable bases
Home-page: https://github.com/WildflowerSchools/wf-airtable-api-schema
License: MIT
Author: Benjamin Jaffe-Talberg
Author-email: ben.talberg@gmail.com
Requires-Python: >=3.9,<4.0
Classifier: Intended Audience :: Developers
Classifier: License :: OSI Approved :: MIT License
Classifier: Operating System :: OS Independent
Classifier: Programming Language :: Python
Classifier: Programming Language :: Python :: 3
Classifier: Programming Language :: Python :: 3.9
Classifier: Programming Language :: Python :: 3.10
Classifier: Programming Language :: Python :: 3.11
Classifier: Programming Language :: Python :: 3.12
Requires-Dist: pydantic (>=2.7.0,<3.0.0)
Project-URL: Repository, https://github.com/WildflowerSchools/wf-airtable-api-schema
